otel_sdk_kfc/__init__.py
otel_sdk_kfc/main.py
otel_sdk_kfc-0.1.1.dist-info/METADATA
otel_sdk_kfc-0.1.1.dist-info/WHEEL
otel_sdk_kfc-0.1.1.dist-info/top_level.txt
otel_sdk_kfc-0.1.1.dist-info/RECORD
