Metadata-Version: 2.1
Name: otel_sdk_kfc
Version: 0.1.1
License: MIT
Requires-Python: >= 3
Requires-Dist: opentelemetry-sdk==1.24.0
Requires-Dist: opentelemetry-exporter-otlp==1.24.0
